sphinx_issues/__init__.py
sphinx_issues-4.0.0.dist-info/LICENSE
sphinx_issues-4.0.0.dist-info/WHEEL
sphinx_issues-4.0.0.dist-info/METADATA
sphinx_issues-4.0.0.dist-info/RECORD
