Metadata-Version: 2.1
Name: sphinx-issues
Version: 4.0.0
Summary: A Sphinx extension for linking to your project's issue tracker
Keywords: sphinx,issues,github
Author-email: Steven Loria <sloria1@gmail.com>
Requires-Python: >=3.8
Classifier: Framework :: Sphinx :: Extension
Classifier: Intended Audience :: Developers
Classifier: License :: OSI Approved :: MIT License
Classifier: Programming Language :: Python :: 3
Classifier: Programming Language :: Python :: 3.8
Classifier: Programming Language :: Python :: 3.9
Classifier: Programming Language :: Python :: 3.10
Classifier: Programming Language :: Python :: 3.11
Classifier: Programming Language :: Python :: 3.12
Classifier: Topic :: Software Development :: Documentation
Requires-Dist: sphinx
Requires-Dist: sphinx-issues[tests] ; extra == "dev"
Requires-Dist: tox ; extra == "dev"
Requires-Dist: pre-commit~=3.6 ; extra == "dev"
Requires-Dist: pytest ; extra == "tests"
Project-URL: Issues, https://github.com/sloria/sphinx-issues/issues
Project-URL: Source, https://github.com/sloria/sphinx-issues
Provides-Extra: dev
Provides-Extra: tests
